cf_clearance-0.31.0.dist-info/METADATA
cf_clearance-0.31.0.dist-info/WHEEL
cf_clearance-0.31.0.dist-info/licenses/LICENSE
cf_clearance/.DS_Store
cf_clearance/__init__.py
cf_clearance/js/__init__.py
cf_clearance/js/canvas.fingerprinting.js
cf_clearance/js/chrome.global.js
cf_clearance/js/chrome.plugin.js
cf_clearance/js/chrome.runtime.js
cf_clearance/js/emulate.touch.js
cf_clearance/js/navigator.permissions.js
cf_clearance/js/navigator.webdriver.js
cf_clearance/retry.py
cf_clearance/stealth.py
cf_clearance-0.31.0.dist-info/RECORD
