Metadata-Version: 2.1
Name: cf_clearance
Version: 0.31.0
Summary: Purpose To make a cloudflare v2 challenge pass successfully, Can be use cf_clearance bypassed by cloudflare, However, with the cf_clearance, make sure you use the same IP and UA as when you got it.
Keywords: cloudflare-bypass cloudflare-scrape anti-bot-page cloudflare cf-clearance
Author-Email: vvanglro <vvanglro@gmail.com>
License: Apache-2.0
Classifier: Programming Language :: Python :: 3
Classifier: Programming Language :: Python :: 3.8
Classifier: Programming Language :: Python :: 3.9
Classifier: Programming Language :: Python :: 3.10
Classifier: Programming Language :: Python :: 3.11
Project-URL: Homepage, https://github.com/vvanglro/cf_clearance
Project-URL: Repository, https://github.com/vvanglro/cf_clearance
Requires-Python: <4,>=3.8
Requires-Dist: playwright
